<?xml version="1.0" encoding="utf-8" ?>
<dwsync>
<file name="abtc.html" server="dsoriano.info" local="131250851372761127" remote="131303466600000000" Dst="0" />
<file name="agrocomex.html" server="dsoriano.info" local="131250851373181127" remote="131303466600000000" Dst="0" />
<file name="consultoria.html" server="dsoriano.info" local="131250851373971127" remote="131303466600000000" Dst="0" />
<file name="dyb.html" server="dsoriano.info" local="131250851375151127" remote="131303467200000000" Dst="0" />
<file name="datacomex.html" server="dsoriano.info" local="131250851374771127" remote="131303467200000000" Dst="0" />
<file name="home.html" server="dsoriano.info" local="131250851372401127" remote="131303467200000000" Dst="0" />
<file name="negocios.html" server="dsoriano.info" local="131250851375491127" remote="131303467200000000" Dst="0" />
<file name="observatorio.html" server="dsoriano.info" local="131250851374391127" remote="131303467200000000" Dst="0" />
<file name="obstaculos.html" server="dsoriano.info" local="131250851375861127" remote="131303467200000000" Dst="0" />
<file name="resultados.html" server="dsoriano.info" local="131292522935008817" remote="131303467200000000" Dst="0" />
<file name="oportunidades.html" server="dsoriano.info" local="131250875429491127" remote="131303467200000000" Dst="0" />
<file name="semanario.html" server="dsoriano.info" local="131292455614768817" remote="131303467200000000" Dst="0" />
<file name="semanario2.html" server="dsoriano.info" local="131292507557188817" remote="131303467200000000" Dst="0" />
</dwsync>